{
	"name": "pp_one_time_load_confirm_layer",
	"properties": {
		"activities": [
			{
				"name": "Onetime_load_confirm_layer",
				"type": "SynapseNotebook",
				"dependsOn": [],
				"policy": {
					"timeout": "0.12:00:00",
					"retry": 0,
					"retryIntervalInSeconds": 30,
					"secureOutput": false,
					"secureInput": false
				},
				"userProperties": [],
				"typeProperties": {
					"notebook": {
						"referenceName": "Onetime_load_confirm",
						"type": "NotebookReference"
					},
					"parameters": {
						"tablename": {
							"value": {
								"value": "@pipeline().parameters.tablename",
								"type": "Expression"
							},
							"type": "string"
						}
					},
					"snapshot": true,
					"sparkPool": {
						"referenceName": "PoolA",
						"type": "BigDataPoolReference"
					},
					"executorSize": "Small",
					"conf": {
						"spark.dynamicAllocation.enabled": false,
						"spark.dynamicAllocation.minExecutors": 12,
						"spark.dynamicAllocation.maxExecutors": 12
					},
					"driverSize": "Small",
					"numExecutors": 12
				}
			}
		],
		"parameters": {
			"table_name": {
				"type": "string",
				"defaultValue": "EXPORT_Product_Category.parquet"
			}
		},
		"folder": {
			"name": "Sales_Project"
		},
		"annotations": []
	}
}